{
   "resources" : {
      "repository" : "http://github.com/rjbs/config-mvp"
   },
   "meta-spec" : {
      "version" : 1.4,
      "url" : "http://module-build.sourceforge.net/META-spec-v1.4.html"
   },
   "generated_by" : "Dist::Zilla version 1.093290",
   "version" : "0.093350",
   "name" : "Config-MVP",
   "author" : [
      "Ricardo Signes <rjbs@cpan.org>"
   ],
   "license" : "perl",
   "requires" : {
      "Tie::IxHash" : "0",
      "Module::Pluggable::Object" : "0",
      "Moose" : "0"
   },
   "abstract" : "multivalue-property package-oriented configuration"
}

